{
    "quiz_title": "Machine Learning",
    "quiz_id": "ASD8FHJ2LK",
    "questions": [
        {
            "question": "What is machine learning?",
            "options": [
                "A",
                "B",
                "C",
                "D"
            ],
            "correct_answer": "A"
        },
        {
            "question": "Which algorithm is commonly used for linear regression?",
            "options": [
                "A",
                "B",
                "C",
                "D"
            ],
            "correct_answer": "B"
        },
        {
            "question": "What is overfitting in machine learning?",
            "options": [
                "A",
                "B",
                "C",
                "D"
            ],
            "correct_answer": "C"
        },
        {
            "question": "What is the purpose of feature scaling in machine learning?",
            "options": [
                "A",
                "B",
                "C",
                "D"
            ],
            "correct_answer": "B"
        },
        {
            "question": "What is the role of activation functions in neural networks?",
            "options": [
                "A",
                "B",
                "C",
                "D"
            ],
            "correct_answer": "A"
        }
    ]
}